aiozk/__init__.py
aiozk/client.py
aiozk/connection.py
aiozk/deadline.py
aiozk/exc.py
aiozk/features.py
aiozk/iterables.py
aiozk/retry.py
aiozk/session.py
aiozk/states.py
aiozk/transaction.py
aiozk/protocol/__init__.py
aiozk/protocol/acl.py
aiozk/protocol/auth.py
aiozk/protocol/check.py
aiozk/protocol/children.py
aiozk/protocol/close.py
aiozk/protocol/connect.py
aiozk/protocol/create.py
aiozk/protocol/data.py
aiozk/protocol/delete.py
aiozk/protocol/exists.py
aiozk/protocol/part.py
aiozk/protocol/ping.py
aiozk/protocol/primitives.py
aiozk/protocol/reconfig.py
aiozk/protocol/request.py
aiozk/protocol/response.py
aiozk/protocol/sasl.py
aiozk/protocol/stat.py
aiozk/protocol/sync.py
aiozk/protocol/transaction.py
aiozk/protocol/watches.py
aiozk/recipes/__init__.py
aiozk/recipes/allocator.py
aiozk/recipes/barrier.py
aiozk/recipes/base_lock.py
aiozk/recipes/base_watcher.py
aiozk/recipes/children_watcher.py
aiozk/recipes/counter.py
aiozk/recipes/data_watcher.py
aiozk/recipes/double_barrier.py
aiozk/recipes/election.py
aiozk/recipes/lease.py
aiozk/recipes/lock.py
aiozk/recipes/party.py
aiozk/recipes/proxy.py
aiozk/recipes/recipe.py
aiozk/recipes/sequential.py
aiozk/recipes/shared_lock.py
aiozk/recipes/tree_cache.py
aiozk/test/__init__.py
aiozk/test/conftest.py
aiozk/test/test_barrier.py
aiozk/test/test_client.py
aiozk/test/test_connection.py
aiozk/test/test_counter.py
aiozk/test/test_election.py
aiozk/test/test_lock.py
aiozk/test/test_recipe.py
aiozk/test/test_session.py
aiozk/test/test_shared_lock.py
aiozk/test/test_transaction.py
aiozk/test/test_treecache.py
aiozk/test/test_watchers.py
aiozk-0.31.1.dist-info/LICENSE
aiozk-0.31.1.dist-info/METADATA
aiozk-0.31.1.dist-info/WHEEL
aiozk-0.31.1.dist-info/top_level.txt
aiozk-0.31.1.dist-info/RECORD
